genomics/__init__.py
genomics/__main__.py
genomics/prompt_response.py
genomics/utils.py
genomics/api/__init__.py
genomics/api/api_client.py
genomics/api/config.py
genomics/api/genomics_client.py
genomics/api/models.py
genomics/api/types.py
genomics/api/genomics_models/__init__.py
genomics/api/genomics_models/models.py
genomics/api/hub/__init__.py
genomics/api/hub/genomics_hub.py
genomics/api/hub/hub_connection_builder.py
genomics/api/hub/hub_response.py
genomics/api/hub/job_status.py
genomics/api/hub/sdk_auth_hub_connection.py
genomics/api/jobs/__init__.py
genomics/api/jobs/jobs.py
genomics/configs/__init__.py
genomics/configs/logger_config.py
tests/__init__.py
tests/test_run_job.py
genomics_product-1.0.0.dist-info/METADATA
genomics_product-1.0.0.dist-info/WHEEL
genomics_product-1.0.0.dist-info/entry_points.txt
genomics_product-1.0.0.dist-info/top_level.txt
genomics_product-1.0.0.dist-info/RECORD
