Metadata-Version: 2.1
Name: genomics-product
Version: 1.0.0
Summary: Genomics Product
Home-page: https://github.com/instadeepai/genomics-product-sdk
Author: InstaDeep Genomics
Author-email: genomics_product@instadeep.com
Requires-Dist: pyyaml ~=6.0.1
Requires-Dist: pydantic ~=1.10.12
Requires-Dist: requests ~=2.32.2
Requires-Dist: jsonpickle ~=2.2.0
Requires-Dist: python-dotenv ~=1.0.1
Requires-Dist: setuptools ~=69.0.3
Requires-Dist: tqdm ~=4.66.2
Requires-Dist: signalrcore ~=0.9.5
Requires-Dist: joblib ~=1.4.2
